coveragefixpaths/__init__.py
coveragefixpaths/__main__.py
coveragefixpaths/coverage.py
coveragefixpaths/junit.py
coveragefixpaths/shared.py
coverage_fixpaths-1.2.0.dist-info/LICENSE
coverage_fixpaths-1.2.0.dist-info/METADATA
coverage_fixpaths-1.2.0.dist-info/WHEEL
coverage_fixpaths-1.2.0.dist-info/entry_points.txt
coverage_fixpaths-1.2.0.dist-info/top_level.txt
coverage_fixpaths-1.2.0.dist-info/RECORD
