Metadata-Version: 2.1
Name: coverage-fixpaths
Version: 1.2.0
Summary: A small CLI tool that automatically fixes paths in Cobertura coverage reports
Home-page: https://github.com/omegacen/coverage-fixpaths
Author: Teake Nutma
License: UNKNOWN
Platform: UNKNOWN
Classifier: Programming Language :: Python :: 3
Classifier: License :: OSI Approved :: GNU Lesser General Public License v3 (LGPLv3)
Classifier: Operating System :: OS Independent
Requires-Python: >=3.6
